EBA_calculator_package/__init__.py
EBA_calculator_package/calculator.py
EBA_calculator_package-0.0.1.dist-info/LICENSE
EBA_calculator_package-0.0.1.dist-info/METADATA
EBA_calculator_package-0.0.1.dist-info/WHEEL
EBA_calculator_package-0.0.1.dist-info/top_level.txt
EBA_calculator_package-0.0.1.dist-info/RECORD
